jmutils/__init__.py
jmutils/show.py
jmutils/times.py
jmUtils-1.0.3.dist-info/METADATA
jmUtils-1.0.3.dist-info/WHEEL
jmUtils-1.0.3.dist-info/top_level.txt
jmUtils-1.0.3.dist-info/RECORD
