Metadata-Version: 2.1
Name: jmUtils
Version: 1.0.3
Summary: Minhas Utilidades
Home-page: https://github.com/jorgemartins72/jmUtils
Author: Jorge Martins
Author-email: jorgemartins72@gmail.com
License: MIT
Platform: UNKNOWN
